[
  {
    "train_name": "JAYENTIKA EXPRESS",
    "train_number": 717,
    "arrival_at_source": "01:11 pm BST",
    "departure_from_source": "01:15 pm BST",
    "arrival_at_destination": "07:00 pm BST",
    "journey_duration": "05:45",
    "operating_days": "Fri, Sat, Sun, Mon, Wed, Thu",
    "source_city": "Brahmanbaria",
    "destination_city": "Sylhet",
    "main_source_city": "Dhaka",
    "main_destination_city": "Sylhet"
  },
  {
    "train_name": "KALNI EXPRESS",
    "train_number": 773,
    "arrival_at_source": "04:46 pm BST",
    "departure_from_source": "04:49 pm BST",
    "arrival_at_destination": "09:30 pm BST",
    "journey_duration": "04:41",
    "operating_days": "Sat, Sun, Mon, Tue, Wed, Thu",
    "source_city": "Brahmanbaria",
    "destination_city": "Sylhet",
    "main_source_city": "Dhaka",
    "main_destination_city": "Sylhet"
  },
  {
    "train_name": "PARABAT EXPRESS",
    "train_number": 709,
    "arrival_at_source": "08:26 am BST",
    "departure_from_source": "08:29 am BST",
    "arrival_at_destination": "01:00 pm BST",
    "journey_duration": "04:31",
    "operating_days": "Fri, Sat, Sun, Tue, Wed, Thu",
    "source_city": "Brahmanbaria",
    "destination_city": "Sylhet",
    "main_source_city": "Dhaka",
    "main_destination_city": "Sylhet"
  }
]