[
  {
    "train_name": "BURIMARI EXPRESS",
    "train_number": 809,
    "arrival_at_source": "01:02 pm BST",
    "departure_from_source": "01:05 pm BST",
    "arrival_at_destination": "03:00 pm BST",
    "journey_duration": "01:55",
    "operating_days": "Fri, Sat, Sun, Mon, Tue, Thu",
    "source_city": "Natore",
    "destination_city": "Bogura",
    "main_source_city": "Dhaka",
    "main_destination_city": "Burimari"
  },
  {
    "train_name": "RANGPUR EXPRESS",
    "train_number": 771,
    "arrival_at_source": "01:43 pm BST",
    "departure_from_source": "01:46 pm BST",
    "arrival_at_destination": "03:36 pm BST",
    "journey_duration": "01:50",
    "operating_days": "Fri, Sat, Sun, Tue, Wed, Thu",
    "source_city": "Natore",
    "destination_city": "Bogura",
    "main_source_city": "Dhaka",
    "main_destination_city": "Rangpur"
  },
  {
    "train_name": "LALMONI EXPRESS",
    "train_number": 751,
    "arrival_at_source": "02:36 am BST",
    "departure_from_source": "02:45 am BST",
    "arrival_at_destination": "04:20 am BST",
    "journey_duration": "01:35",
    "operating_days": "Sat, Sun, Mon, Tue, Wed, Thu",
    "source_city": "Natore",
    "destination_city": "Bogura",
    "main_source_city": "Dhaka",
    "main_destination_city": "Lalmonirhat"
  }
]